blog/__init__.py
blog/adminforms.py
blog/adminx.py
blog/apis.py
blog/apps.py
blog/learn_cache.py
blog/models.py
blog/rss.py
blog/serializers.py
blog/sitemap.py
blog/tests.py
blog/views.py
blog/middleware/__init__.py
blog/middleware/user_id.py
blog/migrations/0001_initial.py
blog/migrations/0002_auto_20200421_1526.py
blog/migrations/0003_auto_20200421_1541.py
blog/migrations/0004_auto_20200428_1152.py
blog/migrations/0005_auto_20200429_1047.py
blog/migrations/0006_post_content_html.py
blog/migrations/0007_post_is_md.py
blog/migrations/__init__.py
comment/__init__.py
comment/adminx.py
comment/apps.py
comment/forms.py
comment/models.py
comment/tests.py
comment/views.py
comment/migrations/0001_initial.py
comment/migrations/0002_auto_20200511_1519.py
comment/migrations/__init__.py
comment/templatetags/__init__.py
comment/templatetags/comment_block.py
config/__init__.py
config/adminx.py
config/apps.py
config/models.py
config/tests.py
config/views.py
config/migrations/0001_initial.py
config/migrations/__init__.py
typeidea/__init__.py
typeidea/autocomplete.py
typeidea/base_admin.py
typeidea/custom_site.py
typeidea/storage.py
typeidea/urls.py
typeidea/wsgi.py
typeidea/media/article_images/2020/05/20/4.gif
typeidea/media/article_images/2020/05/20/5.jpg
typeidea/media/article_images/2020/05/20/6.png
typeidea/media/article_images/2020/05/20/7.png
typeidea/media/article_images/2020/05/20/8.png
typeidea/media/article_images/2020/05/20/8_r6RZj8X.png
typeidea/media/article_images/2020/05/20/9455769fdfe15d1e70109cce22cc4df3.jpg
typeidea/media/article_images/2020/05/20/a2230848687e14385fde490ef0a63526.jpg
typeidea/media/article_images/2020/05/20/lenovo-jetpack-rectangular-snip.jpg
typeidea/media/article_images/2020/05/20/lenovo-jetpack-rectangular-snip_6HlI3pi.jpg
typeidea/media/article_images/2020/05/20/oiryrd.jpg
typeidea/media/article_images/2020/05/21/996586-20170601121117618-1828071635.png
typeidea/settings/__init__.py
typeidea/settings/base.py
typeidea/settings/develop.py
typeidea_heehoo-0.1.dist-info/LICENSE
typeidea_heehoo-0.1.dist-info/METADATA
typeidea_heehoo-0.1.dist-info/WHEEL
typeidea_heehoo-0.1.dist-info/entry_points.txt
typeidea_heehoo-0.1.dist-info/top_level.txt
typeidea_heehoo-0.1.dist-info/RECORD
