Metadata-Version: 2.1
Name: typeidea-heehoo
Version: 0.1
Summary: Blog System base on Django
Home-page: https://www.the5fire.com
Author: heehoo
Author-email: heehoo@qq.com
License: MIT
Platform: UNKNOWN
Classifier: Development Status :: 3 - Alpha
Classifier: Intended Audience :: Developers
Classifier: Topic :: Software Development :: Build Tools
Classifier: License :: OSI Approved :: MIT License
Classifier: Programming Language :: Python :: 3.5
Classifier: Programming Language :: Python :: 3.6
Classifier: Programming Language :: Python :: 3.7
Requires-Dist: django (~=2.0)
Provides-Extra: ipython
Requires-Dist: ipython (==6.2.1) ; extra == 'ipython'
